MORESCA/__init__.py
MORESCA/config.gin
MORESCA/main.py
MORESCA/plotting.py
MORESCA/utils.py
MORESCA/pipeline/__init__.py
MORESCA/pipeline/batch_effect_correction.py
MORESCA/pipeline/clustering.py
MORESCA/pipeline/diff_gene_exp.py
MORESCA/pipeline/feature_selection.py
MORESCA/pipeline/load_data.py
MORESCA/pipeline/neighborhood_graph.py
MORESCA/pipeline/normalization.py
MORESCA/pipeline/pca.py
MORESCA/pipeline/plotting.py
MORESCA/pipeline/quality_control.py
MORESCA/pipeline/scaling.py
MORESCA/pipeline/umap.py
MORESCA/tests/.gitignore
MORESCA/tests/__init__.py
MORESCA/tests/test-config-faulty.gin
MORESCA/tests/test-config.gin
MORESCA/tests/test_analysis_steps.py
MORESCA/tests/test_analysis_steps_no_gin.py
MORESCA/tests/test_clustering.py
MORESCA/tests/test_feature_selection.py
MORESCA/tests/test_main.py
MORESCA/tests/test_normalization.py
MORESCA/tests/test_utils.py
MORESCA/tests/test_validation.py
MORESCA/validation/__init__.py
MORESCA/validation/config_schema.py
MORESCA/validation/config_validation.py
moresca-0.3.0.dist-info/licenses/LICENSE
moresca-0.3.0.dist-info/METADATA
moresca-0.3.0.dist-info/WHEEL
moresca-0.3.0.dist-info/entry_points.txt
moresca-0.3.0.dist-info/top_level.txt
moresca-0.3.0.dist-info/RECORD
